lexicon/__init__.py
lexicon/lexicon.py
lexicon_python-0.1.2.dist-info/licenses/LICENSE
lexicon_python-0.1.2.dist-info/METADATA
lexicon_python-0.1.2.dist-info/WHEEL
lexicon_python-0.1.2.dist-info/top_level.txt
lexicon_python-0.1.2.dist-info/RECORD
