Metadata-Version: 2.4
Name: lexicon-python
Version: 0.1.2
Summary: Python client for the Lexicon DJ API
Author-email: Garrison Burger <burgerga123@gmail.com>
License-Expression: MIT
Project-URL: Homepage, https://github.com/photonicvelocity/lexicon-python
Requires-Python: >=3.9
License-File: LICENSE
Requires-Dist: requests>=2.31
Requires-Dist: tqdm>=4.0
Dynamic: license-file
